TreeView.py
dir2tree_view-1.0.dist-info/LICENSE
dir2tree_view-1.0.dist-info/METADATA
dir2tree_view-1.0.dist-info/WHEEL
dir2tree_view-1.0.dist-info/top_level.txt
dir2tree_view-1.0.dist-info/RECORD
