Metadata-Version: 2.1
Name: dir2tree-view
Version: 1.0
Summary: Print/generate directory tree with icons
Home-page: https://github.com/sarath-pm/dir2tree-view
Author: Sarath P M
Author-email: sarath2375@gmail.com
Classifier: Programming Language :: Python :: 3
Classifier: License :: OSI Approved :: MIT License
Classifier: Operating System :: OS Independent
Requires-Python: >=3.7
License-File: LICENSE
